forge_tests/.staging.env
forge_tests/__init__.py
forge_tests/cv-basic.yml
forge_tests/receive/__init__.py
forge_tests/receive/routes.py
forge_tests/routes/__init__.py
forge_tests/routes/computer_vision/__init__.py
forge_tests/routes/computer_vision/classification/__init__.py
forge_tests/routes/computer_vision/classification/get.py
forge_tests/routes/computer_vision/classification/post.py
forge_tests/routes/computer_vision/object_detection/.gitkeep
forge_tests/routes/computer_vision/object_detection/__init__.py
forge_tests/routes/metadata/.gitkeep
forge_tests/routes/metadata/__init__.py
forge_tests/routes/model_curation/__init__.py
forge_tests/routes/model_curation/upload.py
forge_tests/server.py
forge_tests/utils/__init__.py
forge_tests/utils/cv-basic.yml
forge_tests/utils/model_conversions.py
forge_tests-0.2.0.dist-info/METADATA
forge_tests-0.2.0.dist-info/WHEEL
forge_tests-0.2.0.dist-info/RECORD
